minsearch/__init__.py
minsearch/__version__.py
minsearch/append.py
minsearch/minsearch.py
minsearch/vector.py
minsearch-0.0.6.dist-info/METADATA
minsearch-0.0.6.dist-info/WHEEL
minsearch-0.0.6.dist-info/RECORD
