Metadata-Version: 2.4
Name: minsearch
Version: 0.0.6
Summary: Minimalistic text search engine that uses sklearn and pandas
Project-URL: Homepage, https://github.com/alexeygrigorev/minsearch
Project-URL: Repository, https://github.com/alexeygrigorev/minsearch
Project-URL: Issues, https://github.com/alexeygrigorev/minsearch/issues
Author-email: Alexey Grigorev <alexey@datatalks.club>
Maintainer-email: Alexey Grigorev <alexey@datatalks.club>
License: WTFPL
Keywords: cosine-similarity,search,text-search,tf-idf
Classifier: Development Status :: 4 - Beta
Classifier: Intended Audience :: Developers
Classifier: License :: Other/Proprietary License
Classifier: Programming Language :: Python :: 3
Classifier: Programming Language :: Python :: 3.9
Classifier: Programming Language :: Python :: 3.10
Classifier: Programming Language :: Python :: 3.11
Classifier: Programming Language :: Python :: 3.12
Classifier: Topic :: Software Development :: Libraries :: Python Modules
Classifier: Topic :: Text Processing :: Indexing
Requires-Python: >=3.9
Requires-Dist: numpy
Requires-Dist: pandas
Requires-Dist: scikit-learn
Provides-Extra: dev
Requires-Dist: build; extra == 'dev'
Requires-Dist: hatch; extra == 'dev'
Requires-Dist: pytest; extra == 'dev'
Requires-Dist: requests; extra == 'dev'
